cleanupx.py
cleanupx-2.0.1.dist-info/licenses/LICENSE
cleanupx_core/__init__.py
cleanupx_core/config.py
cleanupx_core/api/__init__.py
cleanupx_core/api/scramble.py
cleanupx_core/api/xai_alt.py
cleanupx_core/api/xai_unified.py
cleanupx_core/processors/__init__.py
cleanupx_core/processors/integrated/__init__.py
cleanupx_core/processors/integrated/api.py
cleanupx_core/processors/integrated/citations.py
cleanupx_core/processors/integrated/cleanup.py
cleanupx_core/processors/integrated/config.py
cleanupx_core/processors/integrated/organization.py
cleanupx_core/processors/integrated/processor.py
cleanupx_core/processors/integrated/snippets.py
cleanupx_core/processors/integrated/utils.py
cleanupx_core/processors/legacy/__init__.py
cleanupx_core/utils/__init__.py
cleanupx-2.0.1.dist-info/METADATA
cleanupx-2.0.1.dist-info/WHEEL
cleanupx-2.0.1.dist-info/entry_points.txt
cleanupx-2.0.1.dist-info/top_level.txt
cleanupx-2.0.1.dist-info/RECORD
